plotpot/__init__.py
plotpot/__main__.py
plotpot/__version__.py
plotpot/battery.py
plotpot/dbmanager.py
plotpot/electrode.py
plotpot/journal.py
plotpot/plot.py
plotpot/plotpot.py
plotpot-1.2.2.dist-info/DESCRIPTION.rst
plotpot-1.2.2.dist-info/METADATA
plotpot-1.2.2.dist-info/RECORD
plotpot-1.2.2.dist-info/WHEEL
plotpot-1.2.2.dist-info/entry_points.txt
plotpot-1.2.2.dist-info/metadata.json
plotpot-1.2.2.dist-info/top_level.txt
plotpot-sample/arbin-merge.txt
plotpot-sample/arbin-merge_1.res
plotpot-sample/arbin-merge_2.res
plotpot-sample/arbin-merge_3.res
plotpot-sample/arbin-merge_4.res
plotpot-sample/arbin-merge_5.res
plotpot-sample/arbintest.res
plotpot-sample/biologic-fullcell.mpt
plotpot-sample/gamrytest.txt
plotpot-sample/gamrytest_1.DTA
plotpot-sample/gamrytest_2.DTA
plotpot-sample/gamrytest_3.DTA
plotpot-sample/gamrytest_4.DTA
plotpot-sample/gamrytest_5.DTA
plotpot-sample/gamrytest_6.DTA
