Metadata-Version: 2.0
Name: plotpot
Version: 1.2.2
Summary: Plot potentiostatic data
Home-page: https://github.com/ahpohl/plotpot
Author: Alexander Pohl
Author-email: alex@ahpohl.com
License: MIT
Keywords: electrochemistry
Platform: UNKNOWN
Classifier: Development Status :: 3 - Alpha
Classifier: Intended Audience :: Science/Research
Classifier: Topic :: Scientific/Engineering :: Visualization
Classifier: License :: OSI Approved :: MIT License
Classifier: Programming Language :: Python :: 3 :: Only
Classifier: Programming Language :: Python :: 3.6
Classifier: Operating System :: OS Independent
Requires-Dist: matplotlib
Requires-Dist: numpy
